terminwind/__init__.py
terminwind/__main__.py
terminwind/app.py
terminwind/button.py
terminwind/custom_scroll_view.py
terminwind/editable_area.py
terminwind/header.py
terminwind/main.py
terminwind/menu.py
terminwind/resizing_directory_tree.py
terminwind/sidebar.py
terminwind/tabs.py
terminwind/terminal/__init__.py
terminwind/terminal/terminal.py
terminwind-0.1.3.dist-info/LICENSE
terminwind-0.1.3.dist-info/WHEEL
terminwind-0.1.3.dist-info/METADATA
terminwind-0.1.3.dist-info/RECORD
