Metadata-Version: 2.1
Name: terminwind
Version: 0.1.3
Summary: A terminal code editor built with Textual
Author: Yubo Wang
Author-email: yubowang2007@gmail.com
Requires-Python: >=3.7,<4.0
Classifier: Programming Language :: Python :: 3
Classifier: Programming Language :: Python :: 3.10
Classifier: Programming Language :: Python :: 3.7
Classifier: Programming Language :: Python :: 3.8
Classifier: Programming Language :: Python :: 3.9
Requires-Dist: aiofile (>=3.7.4,<4.0.0)
Requires-Dist: pyperclip (>=1.8.2,<2.0.0)
Requires-Dist: rich (>=11,<12)
Requires-Dist: textual (>=0.1.15,<0.2.0)
